LICENSE
MANIFEST.in
README.md
requirements.txt
setup.cfg
setup.py
strgen/__init__.py
strgen/apple.py
strgen/config.py
strgen/google.py
strgen/localization.py
strgen/main.py
strgen/util.py
strgen.egg-info/PKG-INFO
strgen.egg-info/SOURCES.txt
strgen.egg-info/dependency_links.txt
strgen.egg-info/entry_points.txt
strgen.egg-info/requires.txt
strgen.egg-info/top_level.txt