Metadata-Version: 2.1
Name: strgen
Version: 1.3.1
Summary: The generate tool of iOS / Android localized strings.
Home-page: https://github.com/daisuke-t-jp/strgen
Author: Daisuke TONOSAKI
Author-email: daisuke.t.jp@gmail.com
License: UNKNOWN
Platform: UNKNOWN
Classifier: Development Status :: 5 - Production/Stable
Classifier: License :: OSI Approved :: MIT License
Classifier: Programming Language :: Python
Classifier: Programming Language :: Python :: 3
Classifier: Programming Language :: Python :: 3.5
Classifier: Programming Language :: Python :: 3.6
Classifier: Programming Language :: Python :: 3.7
Classifier: Programming Language :: Python :: 3.8
Classifier: Topic :: Utilities
